platipy/__init__.py
platipy/backend/README.md
platipy/backend/__init__.py
platipy/backend/api.py
platipy/backend/application.py
platipy/backend/manage.py
platipy/backend/models.py
platipy/backend/sample/SampleClient.ipynb
platipy/backend/sample/__init__.py
platipy/backend/sample/sample.py
platipy/backend/static/css/bootstrap-grid.css
platipy/backend/static/css/bootstrap-grid.css.map
platipy/backend/static/css/bootstrap-grid.min.css
platipy/backend/static/css/bootstrap-grid.min.css.map
platipy/backend/static/css/bootstrap-reboot.css
platipy/backend/static/css/bootstrap-reboot.css.map
platipy/backend/static/css/bootstrap-reboot.min.css
platipy/backend/static/css/bootstrap-reboot.min.css.map
platipy/backend/static/css/bootstrap.css
platipy/backend/static/css/bootstrap.css.map
platipy/backend/static/css/bootstrap.min.css
platipy/backend/static/css/bootstrap.min.css.map
platipy/backend/static/css/dashboard.css
platipy/backend/static/feather/LICENSE
platipy/backend/static/feather/feather.min.js
platipy/backend/static/feather/icons/activity.svg
platipy/backend/static/feather/icons/airplay.svg
platipy/backend/static/feather/icons/alert-circle.svg
platipy/backend/static/feather/icons/alert-octagon.svg
platipy/backend/static/feather/icons/alert-triangle.svg
platipy/backend/static/feather/icons/align-center.svg
platipy/backend/static/feather/icons/align-justify.svg
platipy/backend/static/feather/icons/align-left.svg
platipy/backend/static/feather/icons/align-right.svg
platipy/backend/static/feather/icons/anchor.svg
platipy/backend/static/feather/icons/aperture.svg
platipy/backend/static/feather/icons/archive.svg
platipy/backend/static/feather/icons/arrow-down-circle.svg
platipy/backend/static/feather/icons/arrow-down-left.svg
platipy/backend/static/feather/icons/arrow-down-right.svg
platipy/backend/static/feather/icons/arrow-down.svg
platipy/backend/static/feather/icons/arrow-left-circle.svg
platipy/backend/static/feather/icons/arrow-left.svg
platipy-0.7.2.dist-info/entry_points.txt
platipy-0.7.2.dist-info/WHEEL
platipy-0.7.2.dist-info/METADATA
platipy-0.7.2.dist-info/RECORD
