Metadata-Version: 2.1
Name: platipy
Version: 0.7.2
Summary: Processing Library and Analysis Toolkit for Medical Imaging in Python
License: Apache 2.0 License
Author: Phillip Chlap & Robert Finnegan
Requires-Python: >=3.8.0,<4.0.0
Classifier: Development Status :: 4 - Beta
Classifier: License :: OSI Approved :: Apache Software License
Classifier: License :: Other/Proprietary License
Classifier: Operating System :: OS Independent
Classifier: Programming Language :: Python :: 3
Classifier: Programming Language :: Python :: 3.8
Classifier: Programming Language :: Python :: 3.9
Classifier: Programming Language :: Python :: 3.10
Classifier: Programming Language :: Python :: 3.11
Classifier: Programming Language :: Python :: 3
Classifier: Topic :: Scientific/Engineering :: Image Processing
Classifier: Topic :: Scientific/Engineering :: Medical Science Apps.
Classifier: Topic :: Scientific/Engineering :: Visualization
Provides-Extra: backend
Provides-Extra: cardiac
Provides-Extra: nnunet
Requires-Dist: Flask (>=2.1.0,<3.0.0) ; extra == "backend"
Requires-Dist: Flask-RESTful (>=0.3.8) ; extra == "backend"
Requires-Dist: Flask-SQLAlchemy (>=3.0.2,<4.0.0) ; extra == "backend"
Requires-Dist: Jinja2 (>=3.1,<4.0) ; extra == "backend"
Requires-Dist: SimpleITK (>=2.0.2,<3.0.0)
Requires-Dist: celery (>=5.2.3,<6.0.0) ; extra == "backend"
Requires-Dist: click (>=8.0.3,<9.0.0)
Requires-Dist: gunicorn (>=20.0.4,<23.0.0) ; extra == "backend"
Requires-Dist: matplotlib (>=3.2.2,<4.0.0)
Requires-Dist: nnunet (>=1.7.0,<2.0.0) ; extra == "cardiac" or extra == "nnunet"
Requires-Dist: pandas (>=2.0.3,<3.0.0)
Requires-Dist: psutil (>=5.8.0,<6.0.0) ; extra == "backend"
Requires-Dist: pydicom (>=2.1.2,<3.0.0)
Requires-Dist: pymedphys (>=0.38.0) ; extra == "backend"
Requires-Dist: pynetdicom (>=2.0.2,<3.0.0)
Requires-Dist: redis (>=3.5.3,<5.0.0) ; extra == "backend"
Requires-Dist: requests (>=2.25.1,<3.0.0)
Requires-Dist: rt-utils (>=1.1.4,<2.0.0)
Requires-Dist: scikit-image (>=0.18.1)
Requires-Dist: vtk (>=9.1.0,<10.0.0) ; extra == "cardiac"
